processor.sv
`timescale 1ns / 1ns
`default_nettype none

/*
=== Register Conventions ===
	32 registers each 32b
		REG		ABI		DESCRIPTION					SAVER
		x0		zero	hard-wired zero				-
		x1		ra		return address				caller
		x2		sp		stack pointer				callee
		x3		gp		global pointer				-
		x4		tp		thread pointer				-
		x5		t0		temp / alt link reg			caller
		x6-7	t1-2	temps						caller
		x8		s0/fp	saved reg / frame pointer	callee
		x9		s1		saved reg					callee
		x10-11	a0-1	func args / return values	caller
		x12-17	a2-7	func args					caller
		x18-27	s2-11	saved regs					callee
		x28-31	t3-6	temps						caller
	separate pc 32b
*/

/*
=== Instruction Formats ===
	R-Type (register)
	> 	funct7 [31:25],		rs2 [24:20],	rs1 [19:15],	funct3 [14:12],	rd [11:7],			opcode [6:0]

	I-Type (immediate)
	> 	imm[11:0] [31:20],					rs1 [19:15], 	funct3 [14:12],	rd [11:7], 			opcode [6:0]

	S-Type (store)
	> 	imm[11:5] [31:25], 	rs2 [24:20], 	rs1 [19:15], 	funct3 [14:12],	imm[4:0] [11:7],	opcode [6:0]

	B-Type (branch, variation on S)
	> 	imm[12][10:5] [31:25], rs2 [24:20], rs1 [19:15], 	funct3 [14:12],	imm[4:1][11] [11:7],opcode [6:0]

	U-Type (upper immediate)
	> 	imm[31:12] [31:12],													rd [11:7],			opcode [6:0]

	J-Type (jump, variation on U)
	> 	imm[20][10:1][11] [31:20], 			imm[19:12] [19:12],				rd [11:7],			opcode [6:0]

	Sources      : rs1, rs2
	Desination   : rd

	- Immediates always sign extended (MSB is always the sign bit)
	- In RV32I, lowest two bits (of opcode) is always 11 (can be effectively ignored, but it's illegal)
	- All zero/one bits is not legal
	- Little Endian 0x0A0B0C0D is stored in memory in order n+3, n+2, n+1, n

=== Immediates Produced ===
	I-immediate
	> 	{{25{inst[31]}}, inst[30:25], inst[24:21], inst[20]}

	S-immediate
	> 	{{25{inst[31]}}, inst[30:25], inst[11:8], inst[7]}

	B-immediate
	> 	{{24{inst[31]}}, inst[7], inst[30:25], inst[11:8], 1'b0}

	U-immediate
	>	{inst[31], inst[30:20], inst[19:12], 12'b0}

	J-immediate
	>	{{12{inst[31]}}, inst[19:12}, inst[20], inst{30:25}, inst[24:21], 1'b0}
*/

/*
47 Total Instructions (+ assembler pseudo-instructions ch20)
(^) May reduce instruction count to 38 with these simplifications

=== Register-Immediate Instructions (11) ===
	ADDI rd, rs1, imm
		MV rd, rs1		implemented as ADDI rd, rs1, 0 in assembler
		NOP				as ADDI x0, x0, 0 (only advances pc)
	SLTI, SLITU (set less than immediate)
		SEQZ rd, rs 	implemented as SLTIU rd, rs1, 1
	ANDI, ORI, XORI
		NOT rd, rs		implemented as XORI rd, rs1, -1
	SLLI, SRLI, SRAI (shift left logical, right logical, right arithmetic)
	LUI (load upper immediate)
	AUIPC (add upper immediate to pc)

=== Register-Register Instructions (10) ===
	ADD, SUB
	SLT, SLTU (SNEZ)
	AND, OR, XOR
	SLL, SRL, SRA

=== Control Transfer Instrucitons (pc relative) (8) ===
	JAL (jump and link,  uses J type)
		J	(unconditional jump no link) has rd = x0
	JALR (jump and link register, uses I type)
	# JAL and JALR can generate a misaligned instruction fetch exception when not alined to four-byte boundary

	B (branch, uses B type)
		B{EQ, NE}, {LT, LTU, GE, GEU} and {GT, GTU, LE, LEU} by reversing operands

=== Load Store Instructions (8) ===
	Loads (I type)
		L{W, H, HU, B, BU} (word 32b, halfword 16b signed, hw unsigned, byte 8b signed, byte unsigned)
	Stores (S type)
		S{W, H, B}
	# Loads with rd = x0 must raise exception

=== Memory Model (2) ===
	FENCE (skip, too complex, not necessary for simple processor)
	FENCE.I (same as above)
	^ Might be able to implement both as just NOP (ch2)

=== Control and Status Register Instructions (6) ===
	CSR{RW, RS, RC, RWI, RSI, RCI} (read write, read and set bits, read and clear bits, + unsigned variants)
		Timer (64b): RDCYCLE{-, H}, RDTIME{-, H}, RDINSTRET{-, H} (H stands for high 32b)
		# MUST IMPLEMENT ACCORDING TO MANUAL, FOR PERF ANALYSIS AND OPTIMAZATION
	^ Might be able to cover these instructions with a single SYSTEM instruction

=== Environment Call and Breakpoints (2) ===
	ECALL
	EBREAK
	^ Might be able to cover these instructions with a single SYSTEM instruction

*/

/*
Software Optimization
- Sequential code path should be the most common path, less-frequent paths place out of line
- Software should assume backward branches are predicted taken, forward branches not taken
*/

module pipelined_proc (clk, resetn, temp_sel);
    input logic clk, resetn;
    input logic temp_sel;

	parameter
		LUI 	= 7'b0110111,
		AUIPC 	= 7'b0010111,
		JAL 	= 7'b1101111,
		JALR	= 7'b1100111,
		BEQ		= 7'b1100011,
		BNE		= 7'b1100011,
		BLT		= 7'b1100011,
		BGE		= 7'b1100011,
		BLTU	= 7'b1100011,
		BGEU	= 7'b1100011,
		LB		= 7'b0000011,
		LH		= 7'b0000011,
		LW		= 7'b0000011,
		LBU		= 7'b0000011,
		LBH		= 7'b0000011,
		SB		= 7'b0100011,
		SH		= 7'b0100011,
		SW		= 7'b0100011,
		ADDI	= 7'b0010011,
		SLTI	= 7'b0010011,
		SLTIU	= 7'b0010011,
		XORI	= 7'b0010011,
		ORI		= 7'b0010011,
		ANDI	= 7'b0010011,
		SLLI	= 7'b0010011,
		SRLI	= 7'b0010011,
		SRAI	= 7'b0010011,
		ADD		= 7'b0110011,
		SUB		= 7'b0110011,
		SLL		= 7'b0110011,
		SLT		= 7'b0110011,
		SLTU	= 7'b0110011,
		XOR		= 7'b0110011,
		SRL		= 7'b0110011,
		SRA		= 7'b0110011,
		OR		= 7'b0110011,
		AND		= 7'b0110011;
		// FENCE	= 7'b0001111,
		// FENCE.I	= 7'b0001111,
		// ECALL	= 7'b1110011,
		// EBREAK	= 7'b1110011,
		// CSRRW	= 7'b1110011,
		// CSRRS	= 7'b1110011,
		// CSRRC	= 7'b1110011,
		// CSRRWI	= 7'b1110011,
		// CSRRSI 	= 7'b1110011,
		// CSRRCI 	= 7'b1110011;

    logic [31:0] instr;

	logic [6:0] funct7, opcode;
	logic [4:0] rd, rs1, rs2;
	logic [2:0] funct3;
	assign {funct7, rs2, rs1, funct3, rd, opcode} = instr[31:0];

	logic [31:0] immI, immS, immB, immU, immJ;
	assign immI = {{25{instr[31]}}, instr[30:25], instr[24:21], instr[20]};
	assign immS = {{25{instr[31]}}, instr[30:25], instr[11:8], instr[7]};
	assign immB = {{24{instr[31]}}, instr[7], instr[30:25], instr[11:8], 1'b0};
	assign immU = {instr[31], instr[30:20], instr[19:12], 12'b0};
	assign immJ = {{12{instr[31]}}, instr[19:12], instr[20], instr[30:25], instr[24:21], 1'b0};

    // Fetch
    fetch fetch_stage (.clk(clk),
                       .resetn(resetn),
                       .pcSel(temp_sel),
                       .pcTarget(32'h00000080),
                       .instr(instr));
	
	// // Decode
	// always_ff @(posedge clk) begin
		
	// end

	// // Execute
	// always_ff @(posedge clk) begin
		
	// end

	// // Memory
	// always_ff @(posedge clk) begin
		
	// end

	// // Writeback
	// always_ff @(posedge clk) begin
		
	// end

endmodule


module fetch (clk, resetn, pcSel, pcTarget, instr);
    input  logic clk, resetn, pcSel;
    input  logic [31:0] pcTarget;
    output logic [31:0] instr;

    logic [31:0] pc, pcNext, pcPlus4;

    adder #(.WIDTH(32)) pcIncr (.op0(pc),
                                .op1(32'h4),
                                .out(pcPlus4));

    mux2 #(.WIDTH(32)) pcSelect (.in0(pcPlus4),
                                 .in1(pcTarget),
                                 .sel(pcSel),
                                 .out(pcNext));

    reg_r #(.WIDTH(32)) getPC (.clk(clk),
                               .resetn(resetn),
                               .d(pcNext),
                               .q(pc));

    mem mem1MB (.addr(pc[7:0]),
                .val(instr));
endmodule

// 1MiB instr memory
module mem (addr, val);
    input  logic [7:0]  addr;
    output logic [31:0] val;

    logic [31:0] memArray [0:255];

    initial begin
        $readmemh("program.mem", memArray);
    end

    assign val = memArray[addr];
endmodule

blocks.sv
`timescale 1ns / 1ns
`default_nettype none

module reg_r #(parameter WIDTH = 1) (clk, resetn, d, q);
	input  logic clk, resetn;
	input  logic [WIDTH-1:0] d;
	output logic [WIDTH-1:0] q;

    always_ff @(posedge clk, negedge resetn) begin
        if (!resetn) begin
            q <= 0;
        end
        else begin
            q <= d;
        end
    end
endmodule

module reg_rv #(parameter WIDTH = 1) (clk, resetn, reset_val, d, q);
	input  logic clk, resetn;
	input  logic [WIDTH-1:0] reset_val, d;
	output logic [WIDTH-1:0] q;

    always_ff @(posedge clk, negedge resetn) begin
        if (!resetn) begin
            q <= reset_val;
        end
        else begin
            q <= d;
        end
    end
endmodule

module reg_rc #(parameter WIDTH = 1) (clk, resetn, clear, d, q);
	input  logic clk, resetn, clear;
	input  logic [WIDTH-1:0] d;
	output logic [WIDTH-1:0] q;

    always_ff @(posedge clk, negedge resetn) begin
        if (!resetn) begin
            q <= 0;
        end
        else if (clear) begin
            q <= 0;
        end
        else begin
            q <= d;
        end
    end
endmodule

module reg_re #(parameter WIDTH = 1) (clk, resetn, en, d, q);
	input  logic clk, resetn, clear, en;
	input  logic [WIDTH-1:0] d;
	output logic [WIDTH-1:0] q;

    always_ff @(posedge clk, negedge resetn) begin
        if (!resetn) begin
            q <= 0;
        end
        else if (en) begin
            q <= d;
        end
    end
endmodule

module reg_rce #(parameter WIDTH=1) (clk, resetn, clear, en, d, q);
	input  logic clk, resetn, clear, en;
	input  logic [WIDTH-1:0] d;
	output logic [WIDTH-1:0] q;

    always_ff @(posedge clk, negedge resetn) begin
        if (!resetn) begin
            q <= 0;
        end
        else if (clear) begin
            q <= 0;
        end
        else if (en) begin
            q <= d;
        end
    end
endmodule

module mux2 #(parameter WIDTH=1) (in0, in1, sel, out);
	input  logic [WIDTH-1:0] in0, in1;
	input  logic sel;
	output logic [WIDTH-1:0] out;

	assign out = sel ? in1 : in0;
endmodule

module adder #(parameter WIDTH=1) (op0, op1, out);
	input  logic [WIDTH-1:0] op0, op1;
	output logic [WIDTH-1:0] out;

	assign out = op0 + op1;
endmodule

processor_tb.sv
`timescale 1ns / 1ns
`default_nettype none

module pipelined_proc_tb ();
	logic clk, resetn;
	logic temp_sel;

	initial begin : INIT_RESET
        resetn <= 0;
        #10;
        resetn <= 1;
		#100;
		resetn <= 0;
		#10;
		resetn <= 1;
    end

    initial begin : CLOCK_GEN
        clk <= 1;
        forever #5 clk = ~clk;
    end
    
	initial begin : TEMP_STIM
        temp_sel <= 0;
        #60;
		temp_sel <= 1;
		#10;
		temp_sel <= 0;
    end

	pipelined_proc proc (clk, resetn, temp_sel);

	initial begin
		#150;
		$finish;
	end

	initial begin : VCD
        $dumpfile("proc_tb.vcd");
        $dumpvars(0, pipelined_proc_tb);
    end

endmodule

proc_tb.vcd
$date
	Mon Sep  4 23:24:31 2023
$end
$version
	Icarus Verilog
$end
$timescale
	1ns
$end
$scope module pipelined_proc_tb $end
$var reg 1 ! clk $end
$var reg 1 " resetn $end
$var reg 1 # temp_sel $end
$scope module proc $end
$var wire 1 ! clk $end
$var wire 1 " resetn $end
$var wire 1 # temp_sel $end
$var wire 5 $ rs2 [4:0] $end
$var wire 5 % rs1 [4:0] $end
$var wire 5 & rd [4:0] $end
$var wire 7 ' opcode [6:0] $end
$var wire 32 ( instr [31:0] $end
$var wire 32 ) immU [31:0] $end
$var wire 32 * immS [31:0] $end
$var wire 32 + immJ [31:0] $end
$var wire 32 , immI [31:0] $end
$var wire 32 - immB [31:0] $end
$var wire 7 . funct7 [6:0] $end
$var wire 3 / funct3 [2:0] $end
$var parameter 7 0 ADD $end
$var parameter 7 1 ADDI $end
$var parameter 7 2 AND $end
$var parameter 7 3 ANDI $end
$var parameter 7 4 AUIPC $end
$var parameter 7 5 BEQ $end
$var parameter 7 6 BGE $end
$var parameter 7 7 BGEU $end
$var parameter 7 8 BLT $end
$var parameter 7 9 BLTU $end
$var parameter 7 : BNE $end
$var parameter 7 ; JAL $end
$var parameter 7 < JALR $end
$var parameter 7 = LB $end
$var parameter 7 > LBH $end
$var parameter 7 ? LBU $end
$var parameter 7 @ LH $end
$var parameter 7 A LUI $end
$var parameter 7 B LW $end
$var parameter 7 C OR $end
$var parameter 7 D ORI $end
$var parameter 7 E SB $end
$var parameter 7 F SH $end
$var parameter 7 G SLL $end
$var parameter 7 H SLLI $end
$var parameter 7 I SLT $end
$var parameter 7 J SLTI $end
$var parameter 7 K SLTIU $end
$var parameter 7 L SLTU $end
$var parameter 7 M SRA $end
$var parameter 7 N SRAI $end
$var parameter 7 O SRL $end
$var parameter 7 P SRLI $end
$var parameter 7 Q SUB $end
$var parameter 7 R SW $end
$var parameter 7 S XOR $end
$var parameter 7 T XORI $end
$scope module fetch_stage $end
$var wire 1 ! clk $end
$var wire 1 # pcSel $end
$var wire 32 U pcTarget [31:0] $end
$var wire 1 " resetn $end
$var wire 32 V pcPlus4 [31:0] $end
$var wire 32 W pcNext [31:0] $end
$var wire 32 X pc [31:0] $end
$var wire 32 Y instr [31:0] $end
$scope module getPC $end
$var wire 1 ! clk $end
$var wire 1 " resetn $end
$var wire 32 Z d [31:0] $end
$var parameter 32 [ WIDTH $end
$var reg 32 \ q [31:0] $end
$upscope $end
$scope module mem1MB $end
$var wire 8 ] addr [7:0] $end
$var wire 32 ^ val [31:0] $end
$upscope $end
$scope module pcIncr $end
$var wire 32 _ op0 [31:0] $end
$var wire 32 ` op1 [31:0] $end
$var wire 32 a out [31:0] $end
$var parameter 32 b WIDTH $end
$upscope $end
$scope module pcSelect $end
$var wire 32 c in0 [31:0] $end
$var wire 32 d in1 [31:0] $end
$var wire 1 # sel $end
$var wire 32 e out [31:0] $end
$var parameter 32 f WIDTH $end
$upscope $end
$upscope $end
$upscope $end
$scope begin CLOCK_GEN $end
$upscope $end
$scope begin INIT_RESET $end
$upscope $end
$scope begin TEMP_STIM $end
$upscope $end
$scope begin VCD $end
$upscope $end
$upscope $end
$enddefinitions $end
$comment Show the parameter values. $end
$dumpall
b100000 f
b100000 b
b100000 [
b10011 T
b110011 S
b100011 R
b110011 Q
b10011 P
b110011 O
b10011 N
b110011 M
b110011 L
b10011 K
b10011 J
b110011 I
b10011 H
b110011 G
b100011 F
b100011 E
b10011 D
b110011 C
b11 B
b110111 A
b11 @
b11 ?
b11 >
b11 =
b1100111 <
b1101111 ;
b1100011 :
b1100011 9
b1100011 8
b1100011 7
b1100011 6
b1100011 5
b10111 4
b10011 3
b110011 2
b10011 1
b110011 0
$end
#0
$dumpvars
b100 e
b10000000 d
b100 c
b100 a
b100 `
b0 _
b0 ^
b0 ]
b0 \
b100 Z
b0 Y
b0 X
b100 W
b100 V
b10000000 U
b0 /
b0 .
b0 -
b0 ,
b0 +
b0 *
b0 )
b0 (
b0 '
b0 &
b0 %
b0 $
0#
0"
1!
$end
#5
0!
#10
1"
1!
#15
0!
#20
b1000 -
b1000 *
b1000 &
b1000 W
b1000 Z
b1000 e
b10000000000 (
b10000000000 Y
b10000000000 ^
b100 ]
b1000 V
b1000 a
b1000 c
b100 X
b100 \
b100 _
1!
#25
0!
#30
b10000 -
b10000 *
b10000 &
b1100 W
b1100 Z
b1100 e
b100000000000 (
b100000000000 Y
b100000000000 ^
b1000 ]
b1100 V
b1100 a
b1100 c
b1000 X
b1000 \
b1000 _
1!
#35
0!
#40
b100 -
b100 *
b1000000000000 +
b1000000000000 )
b1 /
b100 &
b10000 W
b10000 Z
b10000 e
b1001000000000 (
b1001000000000 Y
b1001000000000 ^
b1100 ]
b10000 V
b10000 a
b10000 c
b1100 X
b1100 \
b1100 _
1!
#45
0!
#50
b1100 -
b1100 *
b1100 &
b10100 W
b10100 Z
b10100 e
b1011000000000 (
b1011000000000 Y
b1011000000000 ^
b10000 ]
b10100 V
b10100 a
b10100 c
b10000 X
b10000 \
b10000 _
1!
#55
0!
#60
b0 -
b0 *
b10000000000000 +
b10000000000000 )
b10 /
b0 &
b10000000000000 (
b10000000000000 Y
b10000000000000 ^
b10100 ]
b10000000 W
b10000000 Z
b10000000 e
b11000 V
b11000 a
b11000 c
b10100 X
b10100 \
b10100 _
1#
1!
#65
0!
#70
b10000 -
b10000 *
b10010000000000000 +
b10010000000000000 )
b10 %
b10000 &
b10010100000000000 (
b10010100000000000 Y
b10010100000000000 ^
b10000000 ]
b10000100 W
b10000100 Z
b10000100 e
b10000100 V
b10000100 a
b10000100 c
b10000000 X
b10000000 \
b10000000 _
0#
1!
#75
0!
#80
b100 -
b100 *
b10011000000000000 +
b10011000000000000 )
b11 /
b100 &
b10001000 W
b10001000 Z
b10001000 e
b10011001000000000 (
b10011001000000000 Y
b10011001000000000 ^
b10000100 ]
b10001000 V
b10001000 a
b10001000 c
b10000100 X
b10000100 \
b10000100 _
1!
#85
0!
#90
b1100 -
b1100 *
b1100 &
b10001100 W
b10001100 Z
b10001100 e
b10011011000000000 (
b10011011000000000 Y
b10011011000000000 ^
b10001000 ]
b10001100 V
b10001100 a
b10001100 c
b10001000 X
b10001000 \
b10001000 _
1!
#95
0!
#100
b0 -
b0 *
b10100000000000000 +
b10100000000000000 )
b100 /
b0 &
b10010000 W
b10010000 Z
b10010000 e
b10100000000000000 (
b10100000000000000 Y
b10100000000000000 ^
b10001100 ]
b10010000 V
b10010000 a
b10010000 c
b10001100 X
b10001100 \
b10001100 _
1!
#105
0!
#110
b0 +
b0 )
b0 %
b0 /
b0 -
b0 *
b0 &
b100 W
b100 Z
b100 e
b0 (
b0 Y
b0 ^
b0 ]
b100 V
b100 a
b100 c
b0 X
b0 \
b0 _
0"
1!
#115
0!
#120
1"
1!
#125
0!
#130
b1000 -
b1000 *
b1000 &
b1000 W
b1000 Z
b1000 e
b10000000000 (
b10000000000 Y
b10000000000 ^
b100 ]
b1000 V
b1000 a
b1000 c
b100 X
b100 \
b100 _
1!
#135
0!
#140
b10000 -
b10000 *
b10000 &
b1100 W
b1100 Z
b1100 e
b100000000000 (
b100000000000 Y
b100000000000 ^
b1000 ]
b1100 V
b1100 a
b1100 c
b1000 X
b1000 \
b1000 _
1!
#145
0!
#150
b100 -
b100 *
b1000000000000 +
b1000000000000 )
b1 /
b100 &
b10000 W
b10000 Z
b10000 e
b1001000000000 (
b1001000000000 Y
b1001000000000 ^
b1100 ]
b10000 V
b10000 a
b10000 c
b1100 X
b1100 \
b1100 _
1!
